{"stats":{"minecraft:killed":{"minecraft:pig":2,"minecraft:spider":1,"minecraft:creeper":1,"minecraft:skeleton":2,"minecraft:zombie":3,"minecraft:cow":3,"artifacts:mimic":1},"minecraft:custom":{"minecraft:interact_with_furnace":1,"minecraft:mob_kills":15,"minecraft:interact_with_crafting_table":11,"minecraft:open_barrel":5,"minecraft:interact_with_campfire":2,"minecraft:leave_game":3,"minecraft:time_since_death":5165,"minecraft:sleep_in_bed":4,"minecraft:climb_one_cm":4401,"minecraft:time_since_rest":673,"minecraft:sprint_one_cm":64367,"minecraft:damage_taken":2610,"minecraft:walk_one_cm":107081,"minecraft:drop":5,"minecraft:damage_dealt":2342,"minecraft:fly_one_cm":98085,"minecraft:open_chest":5,"minecraft:crouch_one_cm":6623,"minecraft:play_time":50459,"minecraft:sneak_time":17960,"minecraft:deaths":7,"minecraft:walk_under_water_one_cm":97,"minecraft:jump":740,"minecraft:interact_with_blast_furnace":5,"minecraft:walk_on_water_one_cm":11212,"minecraft:total_world_time":50945,"minecraft:fall_one_cm":21192},"minecraft:killed_by":{"minecraft:skeleton":4,"minecraft:creeper":1,"artifacts:mimic":1},"minecraft:picked_up":{"minecraft:charcoal":2,"biomesoplenty:goldenrod":1,"minecraft:leather":2,"minecraft:oak_log":10,"minecraft:dirt":2,"minecraft:string":14,"miners_delight:cave_carrot":5,"minecraft:bone":4,"minecraft:stone_bricks":2,"minecraft:wheat_seeds":1,"minecraft:cobbled_deepslate":2,"minecraft:beef":9,"minecraft:chest":2,"minecraft:oak_planks":2,"minecraft:raw_iron":7,"artifacts:universal_attractor":1,"miners_delight:gossypium":4,"minecraft:acacia_fence":1,"adorablehamsterpets:hamster_guide_book":1,"minecraft:porkchop":5,"minecraft:white_bed":1,"minecraft:spider_eye":1,"alexsmobs:animal_dictionary":1,"minecraft:arrow":2,"minecraft:rotten_flesh":5,"minecraft:hay_block":27,"minecraft:bread":45,"minecraft:oak_sapling":1,"minecraft:coal":3,"minecraft:cobblestone":15},"minecraft:crafted":{"minecraft:wooden_sword":1,"minecraft:oak_planks":40,"minecraft:crafting_table":1,"minecraft:wooden_pickaxe":1,"minecraft:furnace":1,"minecraft:stone_axe":1,"minecraft:bread":81,"minecraft:white_wool":3,"minecraft:stick":12,"minecraft:stone_pickaxe":1,"minecraft:chest":2,"minecraft:white_bed":1,"minecraft:torch":8,"minecraft:wheat":243},"minecraft:mined":{"miners_delight:wild_cave_carrots":4,"minecraft:acacia_leaves":1,"minecraft:grass_block":1,"minecraft:chest":2,"minecraft:campfire":1,"minecraft:oak_planks":2,"minecraft:spawner":1,"minecraft:hay_block":27,"minecraft:grass":1,"minecraft:vine":3,"minecraft:oak_log":10,"minecraft:coal_ore":3,"minecraft:deepslate_iron_ore":7,"minecraft:acacia_fence":1,"minecraft:cobweb":11,"minecraft:stone":15,"minecraft:stone_bricks":2,"minecraft:oak_leaves":1,"minecraft:deepslate":2},"minecraft:used":{"minecraft:stone_pickaxe":43,"minecraft:oak_planks":8,"minecraft:chest":4,"minecraft:wooden_pickaxe":14,"minecraft:torch":8,"minecraft:dirt":1,"minecraft:crafting_table":1,"minecraft:white_bed":2,"minecraft:bread":9,"minecraft:stone_bricks":2,"minecraft:stone_axe":41,"minecraft:wooden_sword":15,"miners_delight:cave_carrot":7,"minecraft:cobblestone":1,"minecraft:furnace":1,"minecraft:oak_sapling":1,"minecraft:acacia_fence":1,"alexsmobs:animal_dictionary":1,"minecraft:cobbled_deepslate":2,"miners_delight:gossypium":4},"minecraft:dropped":{"minecraft:bread":43,"minecraft:wheat_seeds":1,"adorablehamsterpets:hamster_guide_book":1,"alexsmobs:animal_dictionary":1,"minecraft:spider_eye":1}},"DataVersion":3465}